MANIFEST.in
README.rst
setup.py
jenks/README.rst
jenks/__init__.py
jenks/command.py
jenks/data.py
jenks/docs.py
jenks/utils.py
jenks.egg-info/PKG-INFO
jenks.egg-info/SOURCES.txt
jenks.egg-info/dependency_links.txt
jenks.egg-info/entry_points.txt
jenks.egg-info/requires.txt
jenks.egg-info/top_level.txt
jenks/full_tests/__init__.py
jenks/subcommand/__init__.py
jenks/subcommand/build.py
jenks/subcommand/config.py
jenks/subcommand/trigger.py
jenks/subcommand/tests/__init__.py
jenks/subcommand/tests/test_base.py
jenks/subcommand/tests/test_build.py
jenks/subcommand/tests/test_config.py
jenks/subcommand/tests/test_trigger.py
jenks/tests/__init__.py
jenks/tests/test_command.py
jenks/tests/test_data.py
jenks/tests/test_init.py
jenks/tests/test_utils.py