Metadata-Version: 1.1
Name: jenks
Version: 0.2.3
Summary: a jenkins command-line tool
Home-page: http://toumorokoshi.github.io/jenks
Author: Yusuke Tsutsumi
Author-email: yusuke@yusuketsutsumi.com
License: UNKNOWN
Platform: UNKNOWN
Classifier: Development Status :: 4 - Beta
Classifier: Topic :: System :: Software Distribution
Classifier: License :: OSI Approved :: MIT License
Classifier: Programming Language :: Python
Classifier: Programming Language :: Python :: 2.6
Classifier: Programming Language :: Python :: 2.7
